solana/keypair.py
solana_keypair-0.1.0.dist-info/METADATA
solana_keypair-0.1.0.dist-info/WHEEL
solana_keypair-0.1.0.dist-info/top_level.txt
solana_keypair-0.1.0.dist-info/RECORD
