Metadata-Version: 2.2
Name: solana-keypair
Version: 0.1.0
Summary: Provides backwards compatibility for older software versions using solana keypair import
Author-email: handsomevictor <handsomevictor@gmail.com>
Project-URL: Homepage, https://stackoverflow.com/questions/77814538/cannot-import-publickey-from-solana-publickey
Classifier: Programming Language :: Python :: 3
Requires-Python: >=3.8
Requires-Dist: pycryptodome>=3.20.0
Requires-Dist: solana>=0.32.0
Requires-Dist: typing-extensions>=4.2.0
Requires-Dist: semantic-types>=0.1.5
Requires-Dist: base58>=2.1.1
